aind_dft_ephys_analysis/__init__.py
aind_dft_ephys_analysis-0.0.1.dist-info/licenses/LICENSE
aind_dft_ephys_analysis-0.0.1.dist-info/METADATA
aind_dft_ephys_analysis-0.0.1.dist-info/WHEEL
aind_dft_ephys_analysis-0.0.1.dist-info/top_level.txt
aind_dft_ephys_analysis-0.0.1.dist-info/RECORD
